image_invisible_watermarker-0.1.4.dist-info/licenses/LICENSE
image_watermarker/__init__.py
image_watermarker/avif_heif_heif_watermark.py
image_watermarker/jpg_watermark.py
image_watermarker/png_watermark.py
image_watermarker/utilities.py
image_watermarker/webp_watermark.py
image_invisible_watermarker-0.1.4.dist-info/METADATA
image_invisible_watermarker-0.1.4.dist-info/WHEEL
image_invisible_watermarker-0.1.4.dist-info/top_level.txt
image_invisible_watermarker-0.1.4.dist-info/RECORD
