Metadata-Version: 2.4
Name: image-invisible-watermarker
Version: 0.1.4
Summary: A Python package to add and check invisible watermark in image
Author-email: Ateeq Azam <mr.ateeqazam@gmail.com>
License: CC BY-ND
Keywords: image processing,image invisible watermarking,computer vision
Requires-Python: >=3.8
License-File: LICENSE
Requires-Dist: Pillow
Requires-Dist: numpy
Requires-Dist: piexif
Dynamic: license-file
